crcon/__init__.py
crcon/__main__.py
crcon-1.1.2.dist-info/LICENSE.txt
crcon-1.1.2.dist-info/METADATA
crcon-1.1.2.dist-info/WHEEL
crcon-1.1.2.dist-info/entry_points.txt
crcon-1.1.2.dist-info/top_level.txt
crcon-1.1.2.dist-info/RECORD
