Metadata-Version: 2.1
Name: crcon
Version: 1.1.2
Summary: A small extension for chromaconsole for CMD
Author-email: Umit Tasdelen <umittadelen1277@gmail.com>
Project-URL: Homepage, https://github.com/umittadelen/crcon
Project-URL: Bug_Tracker, https://github.com/umittadelen/crcon/issues
Keywords: color,console,terminal,text,style
Classifier: Programming Language :: Python :: 3
Classifier: Programming Language :: Python :: 3.6
Classifier: Programming Language :: Python :: 3.7
Classifier: Programming Language :: Python :: 3.8
Classifier: Programming Language :: Python :: 3.9
Classifier: Programming Language :: Python :: 3.10
Classifier: Programming Language :: Python :: 3.11
Classifier: Programming Language :: Python :: 3.12
Classifier: License :: OSI Approved :: MIT License
Classifier: Operating System :: OS Independent
Requires-Python: >=3
License-File: LICENSE.txt
Requires-Dist: chromaconsole
